einhoorntje_llm_lib/__init__.py
einhoorntje_llm_lib/llm.py
einhoorntje_llm_lib/llm_cache.py
einhoorntje_llm_lib-0.4.dist-info/METADATA
einhoorntje_llm_lib-0.4.dist-info/WHEEL
einhoorntje_llm_lib-0.4.dist-info/top_level.txt
einhoorntje_llm_lib-0.4.dist-info/RECORD
