Metadata-Version: 2.1
Name: einhoorntje-llm-lib
Version: 0.4
Summary: A lib for cached LLM calling and translation
Author: Dmitrii Lukianov
Author-email: unicornporated@gmil.com
Requires-Dist: openai
